tidy_tools/__init__.py
tidy_tools/_types.py
tidy_tools/error.py
tidy_tools/parser.py
tidy_tools/py.typed
tidy_tools/sample.py
tidy_tools/core/__init__.py
tidy_tools/core/_constructor.py
tidy_tools/core/_predicate.py
tidy_tools/core/filter.py
tidy_tools/core/selector.py
tidy_tools/dataframe/__init__.py
tidy_tools/dataframe/context.py
tidy_tools/dataframe/dataframe.py
tidy_tools/dataframe/handler.py
tidy_tools/functions/__init__.py
tidy_tools/functions/merge.py
tidy_tools/functions/reader.py
tidy_tools/model/__init__.py
tidy_tools/model/_types.py
tidy_tools/model/_utils.py
tidy_tools/model/convert.py
tidy_tools/model/model.py
tidy_tools/model/transform.py
tidy_tools/model/validate.py
tidy_tools/model/validators.py
tidy_tools/workflow/__init__.py
tidy_tools/workflow/pipeline.py
tidy_tools-0.3.3.dist-info/METADATA
tidy_tools-0.3.3.dist-info/WHEEL
tidy_tools-0.3.3.dist-info/licenses/LICENSE
tidy_tools-0.3.3.dist-info/RECORD
