Metadata-Version: 2.4
Name: tidy-tools
Version: 0.3.3
Summary: Declarative programming for PySpark workflows.
License-File: LICENSE
Requires-Python: >=3.10
Requires-Dist: attrs
Requires-Dist: loguru
Requires-Dist: pyspark<3.6,>=3.5.0
